pipelayer/__init__.py
pipelayer/context.py
pipelayer/enum.py
pipelayer/event_args.py
pipelayer/exception.py
pipelayer/filter.py
pipelayer/manifest.py
pipelayer/pipeline.py
pipelayer/protocol.py
pipelayer/step.py
pipelayer/switch.py
pipelayer/util.py
pipelayer/_patch/__init__.py
pipelayer/_patch/typing.py
pipelayer-0.7.0.dist-info/LICENSE
pipelayer-0.7.0.dist-info/METADATA
pipelayer-0.7.0.dist-info/WHEEL
pipelayer-0.7.0.dist-info/top_level.txt
pipelayer-0.7.0.dist-info/RECORD
