Metadata-Version: 2.1
Name: pipelayer
Version: 0.7.0
Summary: A lightweight pipeline framework
Home-page: https://github.com/greater-than/PipeLayer
Author: GreaterThan, LLC
Author-email: info@greaterthan.solutions
License: UNKNOWN
Platform: UNKNOWN
Classifier: Intended Audience :: Developers
Classifier: License :: OSI Approved :: MIT License
Classifier: Programming Language :: Python :: 3.7
Classifier: Programming Language :: Python :: 3.8
Classifier: Programming Language :: Python :: 3.9
Classifier: Topic :: Software Development :: Libraries :: Python Modules
Requires-Python: >=3.7
Requires-Dist: pydantic (~=1.8.1)
Requires-Dist: stringbender (~=0.3.0)
